{
  "type": "FeatureCollection",
  "features": [
    {
      "type": "Feature",
      "properties": {
        "stroke": "#555555",
        "stroke-width": 2,
        "stroke-opacity": 1,
        "fill": "#555555",
        "fill-opacity": 0.5
      },
      "geometry": {
        "type": "Polygon",
        "coordinates": [
          [
            [
              7.99530029296875,
              13.301429981673076
            ],
            [
              7.83050537109375,
              13.328157505129283
            ],
            [
              7.418518066406249,
              13.092854552762695
            ],
            [
              7.218017578125001,
              13.106230102044576
            ],
            [
              7.08343505859375,
              12.97511848034919
            ],
            [
              7.086181640625,
              12.87874746308896
            ],
            [
              7.0751953125,
              12.798409949315817
            ],
            [
              7.08343505859375,
              12.744837376819664
            ],
            [
              7.06146240234375,
              12.707329830793384
            ],
            [
              7.033996582031249,
              12.685894460144533
            ],
            [
              7.012023925781249,
              12.677855730564929
            ],
            [
              7.05596923828125,
              12.669816747262848
            ],
            [
              7.06695556640625,
              12.6242577232695
            ],
            [
              7.06695556640625,
              12.567967727957019
            ],
            [
              7.08343505859375,
              12.466078330146832
            ],
            [
              7.07794189453125,
              12.420483239329366
            ],
            [
              7.09991455078125,
              12.374880155986922
            ],
            [
              7.119140625,
              12.321219274328346
            ],
            [
              7.12738037109375,
              12.280966405366836
            ],
            [
              7.152099609375,
              12.21923338786401
            ],
            [
              7.163085937499999,
              12.192388447608373
            ],
            [
              7.174072265624999,
              12.149430892248033
            ],
            [
              7.16033935546875,
              12.11720817346006
            ],
            [
              7.14385986328125,
              12.109151885391997
            ],
            [
              7.14111328125,
              12.068866802422809
            ],
            [
              7.16583251953125,
              12.0473789469445
            ],
            [
              7.20977783203125,
              12.009771062776911
            ],
            [
              7.239990234375,
              11.977531552647788
            ],
            [
              7.248229980468751,
              11.945288193567402
            ],
            [
              7.25921630859375,
              11.90497859698767
            ],
            [
              7.237243652343749,
              11.902291077727055
            ],
            [
              7.218017578125001,
              11.89154073503375
            ],
            [
              7.187805175781251,
              11.88616540437571
            ],
            [
              7.16583251953125,
              11.88078996757037
            ],
            [
              7.16033935546875,
              11.896915959499266
            ],
            [
              7.163085937499999,
              11.84047081265007
            ],
            [
              7.14385986328125,
              11.827029771365764
            ],
            [
              7.11090087890625,
              11.80014570857395
            ],
            [
              7.0751953125,
              11.80014570857395
            ],
            [
              7.05047607421875,
              11.778636560450623
            ],
            [
              7.00927734375,
              11.784014005457767
            ],
            [
              6.96807861328125,
              11.794768579564735
            ],
            [
              6.92962646484375,
              11.754436756202463
            ],
            [
              6.90765380859375,
              11.730234824932992
            ],
            [
              6.891174316406249,
              11.692583158242133
            ],
            [
              6.86920166015625,
              11.657616310322434
            ],
            [
              6.87469482421875,
              11.606502999834897
            ],
            [
              6.8994140625,
              11.582288159945177
            ],
            [
              6.91864013671875,
              11.549998444541838
            ],
            [
              6.92413330078125,
              11.509631071257314
            ],
            [
              6.932373046875,
              11.461182579422236
            ],
            [
              6.921386718749999,
              11.434263158869342
            ],
            [
              6.91864013671875,
              11.418110278178116
            ],
            [
              6.943359374999999,
              11.388494275632903
            ],
            [
              6.998291015625,
              11.366953427299931
            ],
            [
              7.02301025390625,
              11.331946077410558
            ],
            [
              7.033996582031249,
              11.291547655235924
            ],
            [
              7.03948974609375,
              11.267305870377978
            ],
            [
              7.020263671875,
              11.248449735768261
            ],
            [
              6.998291015625,
              11.245755901449789
            ],
            [
              7.03948974609375,
              11.224204320774966
            ],
            [
              7.06695556640625,
              11.21342792694782
            ],
            [
              7.108154296875,
              11.197262582874904
            ],
            [
              7.132873535156249,
              11.173012874215065
            ],
            [
              7.16583251953125,
              11.14876113820503
            ],
            [
              7.187805175781251,
              11.170318336920309
            ],
            [
              7.187805175781251,
              11.208039579322028
            ],
            [
              7.18505859375,
              11.251143544897465
            ],
            [
              7.204284667968749,
              11.280773781192053
            ],
            [
              7.237243652343749,
              11.288854224631772
            ],
            [
              7.28668212890625,
              11.288854224631772
            ],
            [
              7.31689453125,
              11.272693110431502
            ],
            [
              7.341613769531249,
              11.280773781192053
            ],
            [
              7.369079589843751,
              11.299627795341129
            ],
            [
              7.39654541015625,
              11.380416648498276
            ],
            [
              7.41302490234375,
              11.38580175873337
            ],
            [
              7.445983886718749,
              11.366953427299931
            ],
            [
              7.495422363281249,
              11.3696461224437
            ],
            [
              7.53387451171875,
              11.35348957008566
            ],
            [
              7.55859375,
              11.34541095076625
            ],
            [
              7.57781982421875,
              11.326559950463363
            ],
            [
              7.599792480468749,
              11.30232112478806
            ],
            [
              7.62451171875,
              11.30232112478806
            ],
            [
              7.657470703124999,
              11.310400961284474
            ],
            [
              7.71240234375,
              11.326559950463363
            ],
            [
              7.720642089843749,
              11.364260706715516
            ],
            [
              7.731628417968751,
              11.388494275632903
            ],
            [
              7.704162597656249,
              11.410033492843773
            ],
            [
              7.68218994140625,
              11.434263158869342
            ],
            [
              7.679443359375,
              11.48540786584439
            ],
            [
              7.679443359375,
              11.515013722769776
            ],
            [
              7.66845703125,
              11.531161059026699
            ],
            [
              7.676696777343749,
              11.552689396348692
            ],
            [
              7.687683105468749,
              11.579597492622376
            ],
            [
              7.704162597656249,
              11.614574146281976
            ],
            [
              7.737121582031249,
              11.633405912302868
            ],
            [
              7.781066894531249,
              11.64954641194305
            ],
            [
              7.825012207031249,
              11.657616310322434
            ],
            [
              7.86346435546875,
              11.660306224345744
            ],
            [
              7.87445068359375,
              11.676445161005404
            ],
            [
              7.87445068359375,
              11.71947772936839
            ],
            [
              7.855224609374999,
              11.765192487597952
            ],
            [
              7.841491699218749,
              11.794768579564735
            ],
            [
              7.841491699218749,
              11.859287159780411
            ],
            [
              7.822265625000001,
              11.89154073503375
            ],
            [
              7.811279296874999,
              11.939913926868462
            ],
            [
              7.81402587890625,
              11.988278484166859
            ],
            [
              7.852478027343751,
              12.015143939577031
            ],
            [
              7.852478027343751,
              12.052751072179356
            ],
            [
              7.855224609374999,
              12.10109535427938
            ],
            [
              7.84698486328125,
              12.138690418934845
            ],
            [
              7.84423828125,
              12.203126750176567
            ],
            [
              7.833251953125,
              12.246075604574811
            ],
            [
              7.84423828125,
              12.289017472326458
            ],
            [
              7.87994384765625,
              12.353417123726766
            ],
            [
              7.9541015625,
              12.407071396201276
            ],
            [
              8.02276611328125,
              12.412436216375175
            ],
            [
              8.110656738281248,
              12.466078330146832
            ],
            [
              8.13812255859375,
              12.482168801746893
            ],
            [
              8.173828125,
              12.51970934358291
            ],
            [
              8.16558837890625,
              12.610856464703012
            ],
            [
              8.184814453125,
              12.602815372892369
            ],
            [
              8.16009521484375,
              12.64301830574507
            ],
            [
              8.13262939453125,
              12.669816747262848
            ],
            [
              8.140869140625,
              12.71804683823392
            ],
            [
              8.14910888671875,
              12.744837376819664
            ],
            [
              8.16558837890625,
              12.763589068501464
            ],
            [
              8.16009521484375,
              12.78769634352248
            ],
            [
              8.1298828125,
              12.782339370087975
            ],
            [
              8.110656738281248,
              12.79573159051581
            ],
            [
              8.11614990234375,
              12.830548034893301
            ],
            [
              8.13812255859375,
              12.830548034893301
            ],
            [
              8.16009521484375,
              12.84125981830122
            ],
            [
              8.22601318359375,
              12.857326637394761
            ],
            [
              8.272705078125,
              12.851971145225166
            ],
            [
              8.33587646484375,
              12.86268201531027
            ],
            [
              8.38531494140625,
              12.868037278927382
            ],
            [
              8.448486328125,
              12.851971145225166
            ],
            [
              8.50067138671875,
              12.846615538845874
            ],
            [
              8.54736328125,
              12.846615538845874
            ],
            [
              8.58856201171875,
              12.830548034893301
            ],
            [
              8.59954833984375,
              12.79305320327989
            ],
            [
              8.63250732421875,
              12.785017871012084
            ],
            [
              8.66546630859375,
              12.744837376819664
            ],
            [
              8.70391845703125,
              12.73144246130947
            ],
            [
              8.734130859375,
              12.699291778541449
            ],
            [
              8.79730224609375,
              12.685894460144533
            ],
            [
              8.84674072265625,
              12.696612371311604
            ],
            [
              8.90167236328125,
              12.712688391041047
            ],
            [
              8.942871093749998,
              12.744837376819664
            ],
            [
              8.95660400390625,
              12.771625082365382
            ],
            [
              8.975830078125,
              12.785017871012084
            ],
            [
              8.98406982421875,
              12.825191972118773
            ],
            [
              8.942871093749998,
              12.846615538845874
            ],
            [
              8.887939453125,
              12.838581915230744
            ],
            [
              8.84674072265625,
              12.86268201531027
            ],
            [
              8.7890625,
              12.884102383544768
            ],
            [
              8.731384277343748,
              12.894811880984795
            ],
            [
              8.668212890625,
              12.945675729694095
            ],
            [
              8.68743896484375,
              12.92158361893239
            ],
            [
              8.70941162109375,
              12.894811880984795
            ],
            [
              8.55560302734375,
              13.001881592751694
            ],
            [
              8.51715087890625,
              13.028641818911026
            ],
            [
              8.43475341796875,
              13.050047918030097
            ],
            [
              8.360595703125,
              13.07412756381517
            ],
            [
              8.3056640625,
              13.127629468565612
            ],
            [
              8.28643798828125,
              13.170422607388259
            ],
            [
              8.18756103515625,
              13.223903512667826
            ],
            [
              8.15185546875,
              13.255986429192898
            ],
            [
              8.09967041015625,
              13.280045840120149
            ],
            [
              8.05572509765625,
              13.29875706709956
            ],
            [
              8.009033203125,
              13.301429981673076
            ],
            [
              7.99530029296875,
              13.301429981673076
            ]
          ]
        ]
      }
    }
  ]
}